{
  "Origem": "Sydney , Nova Gales do Sul",
  "País": "Austrália",
  "Gênero(s)": "Hard rock , rock and roll , blues rock , heavy metal",
  "Período em atividade": "1973 –presente",
  "Gravadora(s)": "Albert , Atlantic , Columbia , Atco , Elektra , East West , EMI , Epic",
  "Afiliação(ões)": "Geordie, The Easybeats , Dio , Marcus Hook Roll Band",
  "Integrantes": [
    "Angus Young",
    "Phil Rudd",
    "Stevie Young",
    "Brian Johnson",
    "Cliff Williams"
  ],
  "Ex-integrantes": [
    "Malcolm Young",
    "Dave Evans",
    "Larry Van Kriedt",
    "Colin Burgess",
    "Rob Bailey",
    "Peter Clack",
    "Bon Scott",
    "Chris Slade",
    "Mark Evans",
    "Simon Wright",
    "George Young",
    "Axl Rose"
  ],
  "Página oficial": "acdc .com"
}