{
  "Período": [
    "3 de janeiro de 1977",
    "a 3 de janeiro de 1983"
  ],
  "Presidente": "Bill Clinton",
  "Antecessor(a)": "Joe L. Evins",
  "Sucessor(a)": "Jim Cooper",
  "Nome completo": "Albert Arnold Gore, Jr.",
  "Nascimento": [
    "31 de março de 1948 (77 anos)",
    "Washington, D.C. ,",
    "Estados Unidos"
  ],
  "Progenitores": [
    "Mãe: Pauline LaFon Gore",
    "Pai: Albert Gore, Sr."
  ],
  "Alma mater": "Universidade Harvard",
  "Prêmio(s)": "Nobel da Paz (2007)",
  "Esposa": "Tipper Aitcheson (1970–2010)",
  "Filhos(as)": "4",
  "Partido": "Democrata",
  "Religião": "Batista",
  "Profissão": [
    "Jornalista",
    "Ambientalista"
  ],
  "Assinatura": null,
  "Website": "algore.com",
  "Serviço/ramo": "Exército dos Estados Unidos",
  "Anos de serviço": "1969 – 1971",
  "Graduação": "Soldado (Especialista: jornalista)",
  "Unidade": "20ª Brigada de Engenheiros",
  "Conflitos": "Guerra do Vietnã"
}