{
  "No Brasil :": "Ally McBeal: Minha Vida de Solteira",
  "Formato": "série de televisão",
  "Género": "Comédia dramática",
  "Criado por": "David E. Kelley",
  "Escrito por": "David E. Kelley",
  "Elenco": [
    "Calista Flockhart",
    "Courtney Thorne-Smith",
    "Greg Germann",
    "Lisa Nicole Carson",
    "Jane Krakowski",
    "Vonda Shepard",
    "Portia De Rossi",
    "Lucy Liu",
    "James LeGros",
    "Regina Hall",
    "James Marsden",
    "Julianne Nicholson",
    "Josh Hopkins",
    "Hayden Panettiere",
    "com",
    "Gil Bellows",
    "Robert Downey Jr.",
    "Peter MacNicol"
  ],
  "Compositor da música tema": "Vonda Shepard",
  "Tema de abertura": "\"Searchin' My Soul\"",
  "País de origem": "Estados Unidos",
  "Idioma original": "inglês",
  "Temporadas": "5",
  "Episódios": "112",
  "Produtores executivos": [
    "David E. Kelley",
    "Bill D'Elia"
  ],
  "Duração": "42-44 minutos",
  "Emissora": "FOX",
  "Transmissão": "8 de setembro de 1997 – 20 de maio de 2002"
}