{
  "Tipo": "biblioteca nacional , base de dados bibliográfica",
  "Inauguração": "1798 (227 anos)",
  "Membro de": "Société de l'histoire de France , Open Preservation Foundation, World Digital Library , Consortium of European Research Libraries , comunidade internacional GLAM Labs, Geheugen van Nederland, Vereeniging der Vijftig, Conference of European National Librarians, Federação Internacional de Associações e Instituições Bibliotecárias , Open Access Scholarly Publishers Association, Gabinete Europeu de Associações de Bibliotecas, Informação e Documentação , International Internet Preservation Consortium, IIIF Consortium, NAPLE",
  "Diretor(a)": "Wilma van Wezenbeek, Lily Knibbeler",
  "Coordenadas": "52° 4' 50.304\" N 4° 19' 36.3\" E",
  "Localização": "Haia",
  "País": "Países Baixos"
}