{
  "No Brasil": "Valente",
  "Em Portugal": "Brave - Indomável",
  "Gênero": "animação , aventura , épico , fantasia",
  "Direção": [
    "Mark Andrews",
    "Brenda Chapman"
  ],
  "Codireção": "Steve Purcell",
  "Produção": "Katherine Sarafian",
  "Produção executiva": [
    "Pete Docter",
    "John Lasseter",
    "Andrew Stanton"
  ],
  "Roteiro": [
    "Mark Andrews",
    "Steve Purcell",
    "Brenda Chapman",
    "Irene Mecchi"
  ],
  "História": "Brenda Chapman",
  "Narração": "Kelly Macdonald",
  "Elenco": [
    "Kelly Macdonald",
    "Billy Connolly",
    "Emma Thompson",
    "Julie Walters",
    "Kevin McKidd",
    "Craig Ferguson",
    "Robbie Coltrane",
    "John Ratzenberger"
  ],
  "Música": "Patrick Doyle",
  "Cinematografia": [
    "Robert Anderson",
    "Danielle Feinberg"
  ],
  "Edição": "Nicholas C. Smith",
  "Companhia(s) produtora(s)": [
    "Pixar Animation Studios",
    "Walt Disney Pictures"
  ],
  "Distribuição": "Walt Disney Studios Motion Pictures",
  "Lançamento": [
    "22 de junho de 2012",
    "20 de julho de 2012 [ 1 ]",
    "15 de agosto de 2012"
  ],
  "Idioma": "inglês",
  "Orçamento": "US$ 185 milhões [ 2 ]",
  "Receita": "US$ 540.437.063 [ 2 ]"
}