{
  "Género": "animação , aventura",
  "Direção": "Clóvis Vieira",
  "Produção": "Nello de'Rossi",
  "Roteiro": [
    "Clóvis Vieira",
    "Aloisio de Castro",
    "José Feliciano",
    "Robin Geld"
  ],
  "Elenco": [
    "Osmar Prado",
    "Jonas Mello",
    "Aldo César",
    "Marcelo Campos",
    "Cassius Romero",
    "Rosa Maria Barolli"
  ],
  "Música": "Vicent Salvia",
  "Direção de arte": "Clóvis Vieira",
  "Edição": "Marc de Rossi",
  "Companhia(s) produtora(s)": "NDR Filmes",
  "Distribuição": "PlayArte",
  "Lançamento": "1 de fevereiro de 1996 [ 1 ]",
  "Idioma": "português",
  "Orçamento": "R$ 1,5 milhão [ 1 ]"
}