{
  "Nascimento": [
    "William Dennis Weaver",
    "4 de junho de 1924",
    "Joplin"
  ],
  "Morte": [
    "24 de fevereiro de 2006 ( 81 anos )",
    "Ridgway"
  ],
  "Cidadania": "Estados Unidos",
  "Alma mater": [
    "Universidade de Oklahoma"
  ],
  "Ocupação": "ator , piloto , político , ator de televisão , sindicalista , ator de cinema , roteirista , ator de teatro , artista de Voz",
  "Distinções": [
    "Emmy do Primetime de melhor ator coadjuvante em série dramática ( Gunsmoke , 11th Primetime Emmy Awards, 1959)",
    "estrela na calçada da fama de Hollywood",
    "Jane Fonda Humanitarian Award (1987)"
  ],
  "Causa da morte": "câncer"
}