{
  "Formato": "telejornal",
  "Apresentado por": [
    "Jason Kennedy",
    "Giuliana Rancic"
  ],
  "País de origem": "Estados Unidos",
  "Idioma original": "Inglês",
  "Episódios": "7,500+",
  "Editores": [
    "Ryan Seacrest (administrar)",
    "A.J. Benza, Mysteries & Murders"
  ],
  "Duração": "60 minutos",
  "Câmera": "Multicâmera",
  "Formato de imagem": [
    "480i ( SDTV )",
    "1080i ( HDTV )"
  ],
  "Emissora": [
    "E!",
    "E!"
  ],
  "Transmissão": "1º de setembro de 1991 – presente"
}