{
  "Conhecido(a) por": [
    "pesquisa em evolução social",
    "sociobiologia",
    "popularização do termo biodiversidade"
  ],
  "Nascimento": [
    "10 de junho de 1929",
    "Birmingham , Alabama , Estados Unidos"
  ],
  "Morte": [
    "26 de dezembro de 2021 (92 anos)",
    "Burlington , Massachusetts , Estados Unidos"
  ],
  "Nacionalidade": "norte-americano",
  "Cônjuge": "Irene Kelley",
  "Alma mater": [
    "Universidade do Alabama (graduação e mestrado)",
    "Universidade Harvard (doutorado)"
  ],
  "Prêmios": [
    "Prêmio Newcomb Cleveland (1967)",
    "Prêmio Leidy (1979)",
    "Prémio Pulitzer de Não Ficção Geral (1979, 1991)",
    "Prêmio Tyler de Conquista Ambiental (1984)",
    "Prêmio Crafoord (1990)",
    "Medalha Benjamin Franklin por Conquistas de Destaque em Ciências (1998)",
    "Prêmio Kistler (2000)",
    "Prêmio Lewis Thomas (2000)",
    "Prémio Internacional Catalunha (2007)",
    "Prêmios Fronteiras do Conhecimento (2010)",
    "Prêmio Internacional Cosmos (2012)",
    "Kew International Medal (2014)"
  ],
  "Orientador(es)(as)": "Frank M. Carpenter",
  "Instituições": [
    "Universidade Harvard",
    "Universidade Duke"
  ],
  "Campo(s)": "Entomologia e biologia",
  "Tese": "A Monographic Revision of the Ant Genus Lasius (1955) [ 1 ]"
}