{
  "Nascimento": [
    "27 de agosto de 1770",
    "Estugarda ( Sacro Império Romano-Germânico )"
  ],
  "Morte": [
    "14 de novembro de 1831 ( 61 anos )",
    "Berlim ( Confederação Germânica )"
  ],
  "Sepultamento": "Dorotheenstädtischer Friedhof",
  "Cidadania": "Reino de Württemberg",
  "Progenitores": [
    "Georg Ludwig Hegel",
    "Maria Magdalena Louisa Hegel"
  ],
  "Cônjuge": "Marie von Tucher",
  "Filho(a)(s)": "Karl von Hegel",
  "Alma mater": [
    "Universidade de Tubinga",
    "Universidade de Jena",
    "Eberhard-Ludwigs-Gymnasium",
    "Tübinger Stift"
  ],
  "Ocupação": "filósofo , professor universitário , historiador da filosofia , escritor , Jusfilósofo , lógico",
  "Distinções": [
    "Ordem da ÁguiaVermelha 3.ª Classe (1831)"
  ],
  "Empregador(a)": "Universidade de Jena , Universidade de Frederico-Guilherme, Universidade de Heidelberg",
  "Orientador(a)(es/s)": "Friedrich Wilhelm Joseph von Schelling",
  "Obras destacadas": "Lições sobre a filosofia da história, Enciclopédia das ciências filosóficas em compêndio , A Ciência da Lógica , Fenomenologia do Espírito , Princípios da Filosofia do Direito , Lições sobre estética, Lições sobre a filosofia da religião, Lições sobre a história da filosofia",
  "Movimento estético": "Idealismo alemão , historicismo , hegelianismo",
  "Causa da morte": "cólera"
}