{
  "No Brasil": "Hotel Transilvânia 2",
  "Em Portugal": "Hotel Transylvania 2",
  "Género": [
    "animação",
    "comédia",
    "fantasia"
  ],
  "Direção": "Genndy Tartakovsky",
  "Produção": "Michelle Murdocca [ 1 ]",
  "Coprodução": "Skye Lyons",
  "Produção executiva": [
    "Adam Sandler",
    "Allen Covert",
    "Robert Smigel",
    "Ben Waisbren"
  ],
  "Roteiro": [
    "Robert Smigel [ 1 ]",
    "Adam Sandler"
  ],
  "Baseado em": "Personagem, de Todd Durham",
  "Elenco": [
    "Asher Blinkoff",
    "Adam Sandler",
    "Andy Samberg",
    "Selena Gomez",
    "Kevin James",
    "Steve Buscemi",
    "David Spade",
    "Keegan-Michael Key",
    "Fran Drescher",
    "Molly Shannon",
    "Megan Mullally",
    "Nick Offerman",
    "Dana Carvey",
    "Rob Riggle",
    "Mel Brooks"
  ],
  "Música": "Mark Mothersbaugh [ 2 ]",
  "Direção de arte": "Steve Lumley",
  "Edição": "Catherine Apple",
  "Companhia(s) produtora(s)": [
    "Sony Pictures Animation",
    "LStar Capital",
    "Media Rights Capital"
  ],
  "Distribuição": [
    "Columbia Pictures",
    "Sony Pictures Brasil",
    "Big Picture Films"
  ],
  "Lançamento": [
    "25 de setembro de 2015",
    "24 de setembro de 2015",
    "10 de dezembro de 2015"
  ],
  "Idioma": "inglês",
  "Orçamento": "US$ 80 Milhões",
  "Receita": "US$ 473.226.958"
}