{
  "No Brasil": "Kung Fu Panda 2",
  "Em Portugal": "O Panda do Kung Fu 2",
  "Gênero": "animação",
  "Direção": "Jennifer Yuh Nelson",
  "Produção": "Melissa Cobb",
  "Roteiro": [
    "Jonathan Aibel",
    "Glenn Berger"
  ],
  "Baseado em": [
    "Personagens criados por",
    "Ethan Reiff & Cyrus Voris"
  ],
  "Elenco": [
    "Jack Black",
    "Angelina Jolie",
    "Dustin Hoffman",
    "Gary Oldman",
    "Jackie Chan",
    "Seth Rogen",
    "Lucy Liu",
    "David Cross"
  ],
  "Música": [
    "Hans Zimmer",
    "John Powell"
  ],
  "Edição": "Clare Knight",
  "Companhia(s) produtora(s)": "DreamWorks Animation",
  "Distribuição": "Paramount Pictures",
  "Lançamento": [
    "22 de maio de 2011 ( 2011-05-22 ) ( Hollywood )",
    "26 de maio de 2011 ( 2011-05-26 ) (EUA)",
    "9 de junho de 2011 ( 2011-06-09 ) (PRT) [ 1 ] [ 2 ]",
    "10 de junho de 2011 ( 2011-06-10 ) (BRA) [ 3 ]"
  ],
  "Idioma": "inglês",
  "Orçamento": "US$ 150 milhões [ 4 ]",
  "Receita": "US$ 665 692 281 [ 5 ]"
}