{
  "Gênero": "ação",
  "Direção": "Brian De Palma",
  "Produção": [
    "Tom Cruise",
    "Paula Wagner"
  ],
  "Produção executiva": "Paul Hitchcock",
  "Roteiro": [
    "David Koepp",
    "Robert Towne"
  ],
  "História": [
    "David Koepp",
    "Steven Zaillian"
  ],
  "Baseado em": "Mission: Impossible , de Bruce Geller",
  "Elenco": [
    "Tom Cruise",
    "Jon Voight",
    "Emmanuelle Béart",
    "Henry Czerny",
    "Jean Reno",
    "Ving Rhames",
    "Kristin Scott Thomas",
    "Vanessa Redgrave"
  ],
  "Música": "Danny Elfman",
  "Cinematografia": "Stephen H. Burum",
  "Direção de arte": "Norman Reynolds",
  "Figurino": "Penny Rose",
  "Edição": "Paul Hirsch",
  "Companhia(s) produtora(s)": "Cruise/Wagner Productions",
  "Distribuição": "Paramount Pictures",
  "Lançamento": [
    "22 de maio de 1996 ( 1996-05-22 ) (Estados Unidos) [ 1 ] [ 2 ] [ 3 ]",
    "12 de julho de 1996 ( 1996-07-12 ) (Brasil) [ 4 ]"
  ],
  "Idioma": "inglês",
  "Orçamento": "US$ 80 milhões [ 1 ]",
  "Receita": "US$ 457 696 391 [ 1 ]"
}