{
  "No Brasil :": "New Girl",
  "Em Portugal :": "Jess e os Rapazes",
  "Formato": "sitcom",
  "Gênero": "comédia",
  "Criado por": "Elizabeth Meriwether",
  "Elenco": [
    "Zooey Deschanel",
    "Jake Johnson",
    "Max Greenfield",
    "Lamorne Morris",
    "Hannah Simone"
  ],
  "Tema de abertura": "Hey Girl por Zooey Deschanel [ 1 ]",
  "País de origem": "Estados Unidos",
  "Idioma original": "inglês",
  "Temporadas": "7",
  "Episódios": "146 ( lista de episódios )",
  "Duração": "22 minutos",
  "Câmera": "Câmera única",
  "Formato de imagem": "1080i ( HDTV )",
  "Emissora": "Fox",
  "Transmissão": "20 de setembro de 2011 ( 2011-09-20 ) – 15 de maio de 2018 ( 2018-05-15 )"
}