{
  "Nascimento": [
    "11 de outubro de 1976 (48 anos)",
    "New Orleans , Louisiana"
  ],
  "Residência": "Mountain View , Califórnia",
  "Cidadania": "Estados Unidos",
  "Etnia": "Indiana",
  "Cônjuge": "Umaima Marvi [ 1 ]",
  "Alma mater": [
    "Instituto Tecnológico de Massachusetts ( BS , MS )",
    "Universidade de Harvard ( MBA )"
  ],
  "Ocupação": [
    "educador ,",
    "diretor executivo"
  ],
  "Distinções": [
    "Prémios Princesa das Astúrias (2019)"
  ],
  "Orientador(a)(es/s)": "Marcelo Hehl Cintra"
}