{
  "Período": [
    "1 de fevereiro de 2025",
    "até 7 de fevereiro de 2025"
  ],
  "Presidente": "Donald Trump",
  "Antecessor(a)": "Rohit Chopra",
  "Sucessor(a)": "Russ Vought",
  "Nome completo": "Scott Kenneth Homer Bessent",
  "Nascimento": [
    "21 de agosto de 1962 (62 anos)",
    "Conway , Carolina do Sul , Estados Unidos"
  ],
  "Nacionalidade": "norte-americano",
  "Alma mater": "Universidade Yale ( BA )",
  "Cônjuge": "John Freeman ( c. 2011)",
  "Filhos(as)": "4",
  "Partido": "Republicano",
  "Profissão": "investidor e gestor de fundos"
}