{
  "Gentílico": "Southerner [ 1 ]",
  "Subregiões": [
    "Sudeste dos Estados Unidos",
    "Deep South",
    "Atlântico Sul"
  ],
  "País": "Estados Unidos",
  "Estados": [
    "Alabama",
    "Arkansas",
    "Delaware",
    "Flórida",
    "Geórgia",
    "Kentucky",
    "Luisiana",
    "Maryland",
    "Mississípi",
    "Carolina do Norte",
    "Oklahoma",
    "Carolina do Sul",
    "Tennessee",
    "Texas",
    "Virgínia",
    "Virgínia Ocidental"
  ],
  "Distrito federal": "Distrito de Colúmbia",
  "Área total": "2,384,143 km²",
  "População total 2020 [ 2 ]": "126 266 107 hab."
}