{
  "Razão social": [
    "Turner Broadcasting System Inc.",
    "Superstation Inc."
  ],
  "Tipo anterior": "Subsidiária (1996-2019)",
  "Atividade": [
    "Mídia",
    "Entretenimento",
    "Mídia interativa"
  ],
  "Fundação": "12 de maio de 1965",
  "Fundador(es)": "Robert Edward \"Ted\" Turner",
  "Destino": "Dissolução da Turner devido a reestruturação da WarnerMedia . Seus ativos foram para outras divisões da Warner Bros.",
  "Encerramento": "4 de março de 2019",
  "Sede": "Atlanta , Estados Unidos",
  "Proprietário(s)": "Warner Bros.",
  "Produtos": [
    "Emissoras de Televisão",
    "TV por Assinatura"
  ],
  "Divisões": [
    "Turner Broadcasting System Europa",
    "Turner Broadcasting System América Latina",
    "Turner Broadcasting System Ásia e Pacífico"
  ],
  "Subsidiárias": [
    "Cartoon Network Studios",
    "Hanna-Barbera Studios Europe",
    "Williams Street Productions",
    "CNN Films",
    "Turner Sports",
    "Bleacher Report",
    "Turner Private Networks",
    "Lazy Town Entertainment"
  ],
  "Sucessora(s)": "Warner Bros. Discovery Networks Warner Bros. Discovery Sports CNN Global (Arquivo)",
  "Website oficial": "www .international .tbs .com"
}