{
  "Tipo": "Rede de televisão aberta",
  "País": "Estados Unidos",
  "Fundação": [
    "1955 como KWEX-TV",
    "por Raoul A. Cortez"
  ],
  "Pertence a": "TelevisaUnivision",
  "Proprietário": "TelevisaUnivision",
  "Sede": "Los Angeles , CA , Estados Unidos",
  "Slogan": [
    "La que nos une",
    "A que nos une ( pt )"
  ],
  "Cobertura": "Estados Unidos",
  "Cobertura internacional": "Porto Rico",
  "Nome(s) anterior(es)": [
    "KWEX-TV ( 1955 até 1961 )",
    "S panish I nternational N etwork ( 1961 até 1986 )"
  ],
  "Página oficial": "http://www.univision.com",
  "Digital": [
    "23 UHF ( Miami )",
    "34 UHF ( Los Angeles )",
    "41 UHF ( Nova Iorque )"
  ]
}