{
  "Lema": [
    "Veritas",
    "\"Verdade\" [ 1 ]"
  ],
  "Fundação": "1636 ; há 388 anos [ 2 ]",
  "Tipo de instituição": "Privada sem fins lucrativos",
  "Localização": "Cambridge , Massachusetts , Estados Unidos",
  "Presidente": "Alan Garber",
  "Total de estudantes": "22.000 [ 3 ]",
  "Graduação": [
    "7 181 total",
    "4,671 Faculdade [ 4 ]",
    "526 Extensão"
  ],
  "Pós-graduação": "15.250 [ 3 ]",
  "Campus": [
    "Urbano",
    "210 acre (85,0 ha)"
  ],
  "Jornal": "The Harvard Crimson",
  "Cores": "Carmesim, branco, e preto [ 5 ]",
  "Mascote": "Crimson",
  "Afiliações": [
    "NAICU",
    "AICUM",
    "AAU",
    "URA",
    "NCAA Division I – Ivy League"
  ],
  "Orçamento anual": "US$ 53,2 bilhões [ 6 ]",
  "Página oficial": "harvard .edu"
}