{
  "Origem": "Londres , Inglaterra [ 1 ]",
  "País": "Reino Unido",
  "Gênero(s)": [
    "Rock progressivo [ 1 ]",
    "art rock",
    "pop rock",
    "rock psicodélico"
  ],
  "Período em atividade": [
    "1968–1981",
    "1983–2004",
    "2008–presente"
  ],
  "Gravadora(s)": "Atlantic Records",
  "Integrantes": [
    "Jon Davison",
    "Steve Howe",
    "Geoff Downes",
    "Alan White",
    "Billy Sherwood"
  ],
  "Ex-integrantes": [
    "Chris Squire",
    "Jon Anderson",
    "Rick Wakeman",
    "Bill Bruford",
    "Tony Kaye",
    "Trevor Rabin",
    "Peter Banks",
    "Patrick Moraz",
    "Trevor Horn",
    "Igor Khoroshev",
    "Benoît David",
    "Oliver Wakeman"
  ],
  "Página oficial": "www.yesworld.com"
}